USports_Scraper/__init__.py
USports_Scraper/common_util.py
USports_Scraper/scrape_game_box.py
USports_Scraper/scrape_game_ids.py
USports_Scraper/scrape_season_box.py
usports_scraper-0.0.4.dist-info/METADATA
usports_scraper-0.0.4.dist-info/WHEEL
usports_scraper-0.0.4.dist-info/licenses/LICENCE
usports_scraper-0.0.4.dist-info/RECORD
