Metadata-Version: 2.1
Name: USports_Scraper
Version: 0.0.4
Summary: Tool to quickly retrieve data from the USports Hoops website
Project-URL: Homepage, https://github.com/bonobo-friend/usports-hoops-scraper
Project-URL: Bug Tracker, https://github.com/bonobo-friend/usports-hoops-scraper/issues
Author-email: Owen Rocchi <orocchi27@gmail.com>
License-File: LICENCE
Classifier: License :: OSI Approved :: MIT License
Classifier: Operating System :: OS Independent
Classifier: Programming Language :: Python :: 3
Requires-Python: >=3.7
